{
  "Грипп": ["кашель", "боль в горле", "головная боль", "насморк", "температура", "слабость"],
  "Простуда": ["Насморк", "Слабость", "температура"],
  "Мигрень": ["головная боль", "тошнота", "головокружение", "рвота", "отсутствие сна", "боли в шее", "повышенная жажда", "запоры", "чувствительность к звукам", "чувствительность к свету", "чувствительность к запахам"],
  "Грипп": ["кашель", "боль в горле", "головная боль", "насморк", "температура", "слабость"],
  "Простуда": ["Насморк", "Слабость", "температура"],
  "Мигрень": ["головная боль", "тошнота", "головокружение"],
  "Астма": ["Одышка", "Сухой кашель", "Чихание"],
  "Ангина": ["Боль при глотании", "Отечность лимфоузлов", "Повышенная температура"],
  "Сахарный диабет": ["Повышенная жажда", "Частое мочеиспускание", "Усталость"],
  "Гастрит": ["Боль в животе", "Изжога", "Тошнота"],
  "Остеоартрит": ["Боль в суставах", "Отек суставов", "Снижение подвижности"],
  "Аллергия": ["Красные глаза", "Зуд в носу", "Одышка"],
  "Эпилепсия": ["Потеря сознания", "Судороги", "Замедленное восстановление"],
  "Гипертония": ["Головная боль", "Высокое давление", "Сердцебиение"],
  "Гастроэнтерит": ["Рвота", "Понос", "Боль в животе"],
  "Гипотиреоз": ["Усталость", "Приливы холода", "Прибавка веса"],
  "Гипертиреоз": ["Нервозность", "Потеря веса", "Повышенная потливость"],
  "Цистит": ["Боль при мочеиспускании", "Частые посещения туалета", "Нижние боли в животе"],
  "Миопия": ["Размытость зрения", "Утомляемость глаз", "Головные боли"],
  "Депрессия": ["Потеря интереса к жизни", "Бессонница", "Пониженное настроение"],
  "Анемия": ["Слабость", "Бледность кожи", "Головокружение"],
  "Бронхит": ["Кашель с мокротой", "Затрудненное дыхание", "Повышенная температура"],
  "Грибковая инфекция кожи": ["Зуд", "Покраснение", "Лущение кожи"],
  "Артрит": ["Суставные боли", "Опухание суставов", "Ограничение движения"],
  "Панкреатит": ["Боль в верхней части живота", "Рвота", "Нарушение аппетита"],
  "Мочекаменная болезнь": ["Боль в пояснице", "Кровь в моче", "Частые мочекаменные приступы"],
  "Шизофрения": ["Бред", "Замедленная реакция", "Снижение социальной активности"],
  "Миастения": ["Слабость мышц", "Одышка", "Затрудненное глотание"],
  "Псориаз": ["Покраснение кожи", "Высыпания", "Зуд"],
  "Ожирение": ["Избыточный вес", "Затрудненное дыхание", "Сахарный диабет"],
  "Геморрой": ["Кровотечение", "Зуд и жжение", "Боль в области заднего прохода"],
  "Гепатит": ["Желтушность кожи и глаз", "Темная моча", "Боль в правом боку"],
  "Сердечная недостаточность": ["Одышка", "Опухание ног", "Усталость"],
  "Остеопороз": ["Костные боли", "Повышенный риск переломов", "Снижение роста"],
  "Тиреотоксикоз": ["Нервозность", "Потеря веса", "Повышенная потливость"],
  "Экзема": ["Зуд", "Высыпания", "Покраснение кожи"]
}
